printbuddies/__init__.py
printbuddies/buds.py
printbuddies/colormap.py
printbuddies/gradient.py
printbuddies/grid.py
printbuddies/progress.py
printbuddies/py.typed
printbuddies-2.1.3.dist-info/METADATA
printbuddies-2.1.3.dist-info/WHEEL
printbuddies-2.1.3.dist-info/licenses/LICENSE.txt
printbuddies-2.1.3.dist-info/RECORD
