Metadata-Version: 2.1
Name: printbuddies
Version: 2.1.3
Summary: Various printing utilities and helpers/extenders for the `rich` package.
Project-URL: Homepage, https://github.com/matt-manes/printbuddies
Project-URL: Documentation, https://github.com/matt-manes/printbuddies/tree/main/docs
Project-URL: Source code, https://github.com/matt-manes/printbuddies/tree/main/src/printbuddies
Author: Matt Manes
License-File: LICENSE.txt
Keywords: print,printing,progressbar,terminal
Classifier: License :: OSI Approved :: MIT License
Classifier: Operating System :: OS Independent
Classifier: Programming Language :: Python :: 3
Requires-Python: >=3.10
Requires-Dist: noiftimer
Requires-Dist: rich
Requires-Dist: typing-extensions
